smalltools_st/__init__.py
smalltools_st/behavior/__init__.py
smalltools_st/behavior/cascading.py
smalltools_st/behavior/suitable_class_finder.py
smalltools_st-0.2.2.dist-info/LICENSE
smalltools_st-0.2.2.dist-info/METADATA
smalltools_st-0.2.2.dist-info/WHEEL
smalltools_st-0.2.2.dist-info/RECORD
