Metadata-Version: 2.1
Name: smalltools-st
Version: 0.2.2
Summary: A Python port with a few small tools, snippets and utils (with a lot of WIP) learned in my times as a Smalltalk developer and which I miss a lot.
Home-page: https://github.com/EzequielPuerta/smalltools
License: MIT
Author: Armando Ezequiel Puerta
Author-email: armando.ezequiel.puerta@gmail.com
Requires-Python: >=3.7,<4.0
Classifier: Development Status :: 5 - Production/Stable
Classifier: Intended Audience :: Developers
Classifier: License :: OSI Approved :: MIT License
Classifier: Operating System :: OS Independent
Classifier: Programming Language :: Python :: 3
Classifier: Programming Language :: Python :: 3.7
Classifier: Programming Language :: Python :: 3.8
Classifier: Programming Language :: Python :: 3.9
Classifier: Programming Language :: Python :: 3.10
Classifier: Programming Language :: Python :: 3.11
Classifier: Topic :: Software Development
Project-URL: Bug Tracker, https://github.com/EzequielPuerta/smalltools/issues
Project-URL: Documentation, https://github.com/EzequielPuerta/smalltools
Project-URL: Repository, https://github.com/EzequielPuerta/smalltools
